Metadata-Version: 2.1
Name: color-gradient-generator
Version: 1.3.1
Summary: This package will generate a color gradient. The colors, the number of colors generated, the color format, the hexadecimal prefix are configurable.
Author: Mr. PRAINGLE
License-File: LICENSE
